[
    {
        "title": "What is Meta Gate?",
        "content": [
                   "- Meta Gate is an admin tool to search / register / manage claim topics & achievements.\n",
                   "- Meta Gate is open to any participants of Metadium platform, but functions to register\nnew claim topics & achievements are currently limited to registered AAs."
            ]
    },
    {
        "title": "What is Claim / Achievement?",
        "content": [
            "- Claim is a proof of identity attributes that improve reliability of identity data online. AAs can verify the authenticity of user data on its own way, and issue claim for it upon user's request.\n",
            "- Achievement is a reward mechanism triggered by claims designed to incentivize users to onboard onto and fully experience the service. It helps to acquire valuable claims on platform."
            ]
    },
    {
        "title": "How do I add Achievement?",
        "content": [
            "Add achievement."
            ]
    },
    {
        "title": "How do I add balance to an Achievement?",
        "content": [
            "Add balance"
            ]
    },
    {
        "title": "How much transaction fee is required for each action?",
        "content": [
            "Transaction Fee"
            ]
    }
]
